granita/__init__.py
granita/__main__.py
granita/config.py
granita/granita.config.json
granita/transform.py
granita/init/pages/index.md
granita/init/static/index.css
granita/init/templates/index.html
granita-0.3.0.dist-info/entry_points.txt
granita-0.3.0.dist-info/LICENSE
granita-0.3.0.dist-info/WHEEL
granita-0.3.0.dist-info/METADATA
granita-0.3.0.dist-info/RECORD
