Metadata-Version: 2.1
Name: granita
Version: 0.3.0
Summary: Granita is a simple static site generator for embedding Markdown in HTML templates.
Author: apple-phi
Requires-Python: >=3.6
Requires-Dist: markdown ~=3.3
Requires-Dist: python-frontmatter ~=1.0
Requires-Dist: pyquery ~=1.4
Requires-Dist: typer ~=0.4
Project-URL: Home, https://github.com/apple-phi/granita
